chartpress.py
chartpress-2.3.0.dist-info/LICENSE
chartpress-2.3.0.dist-info/METADATA
chartpress-2.3.0.dist-info/WHEEL
chartpress-2.3.0.dist-info/entry_points.txt
chartpress-2.3.0.dist-info/top_level.txt
chartpress-2.3.0.dist-info/RECORD
