Metadata-Version: 2.2
Name: chartpress
Version: 2.3.0
Summary: ChartPress: render and publish helm charts and images
Home-page: https://github.com/jupyterhub/chartpress
Author: Jupyter Development Team
Author-email: jupyter@googlegroups.com
License: BSD
Keywords: helm,kubernetes
Platform: Linux
Platform: Mac OS X
Classifier: Intended Audience :: Developers
Classifier: Intended Audience :: System Administrators
Classifier: License :: OSI Approved :: BSD License
Classifier: Programming Language :: Python
Classifier: Programming Language :: Python :: 3
Requires-Python: >=3.7
License-File: LICENSE
Requires-Dist: ruamel.yaml>=0.15.44
Requires-Dist: docker!=5.0.0,>=3.2.0
Dynamic: author
Dynamic: author-email
Dynamic: classifier
Dynamic: description
Dynamic: description-content-type
Dynamic: home-page
Dynamic: keywords
Dynamic: license
Dynamic: platform
Dynamic: requires-dist
Dynamic: requires-python
Dynamic: summary
